testnet/__init__.py
testnet-0.0.1.dist-info/METADATA
testnet-0.0.1.dist-info/WHEEL
testnet-0.0.1.dist-info/top_level.txt
testnet-0.0.1.dist-info/RECORD
